MANIFEST.in
setup.py
docs/HISTORY.txt
src/dolmen/__init__.py
src/dolmen.authentication.egg-info/PKG-INFO
src/dolmen.authentication.egg-info/SOURCES.txt
src/dolmen.authentication.egg-info/dependency_links.txt
src/dolmen.authentication.egg-info/namespace_packages.txt
src/dolmen.authentication.egg-info/not-zip-safe
src/dolmen.authentication.egg-info/requires.txt
src/dolmen.authentication.egg-info/top_level.txt
src/dolmen/authentication/README.txt
src/dolmen/authentication/__init__.py
src/dolmen/authentication/configure.zcml
src/dolmen/authentication/events.py
src/dolmen/authentication/interfaces.py
src/dolmen/authentication/principal.py
src/dolmen/authentication/tests/__init__.py
src/dolmen/authentication/tests/ftesting.zcml
src/dolmen/authentication/tests/test_package.py