Metadata-Version: 1.0
Name: dolmen.authentication
Version: 0.3
Summary: Authentication for Grok applications
Home-page: http://www.dolmen-project.org
Author: Souheil Chelfouh
Author-email: souheil@chelfouh.com
License: GPL
Download-URL: http://pypi.python.org/pypi/dolmen.authentication
Keywords: Grok Zope3 Dolmen
Platform: Any
Classifier: Development Status :: 4 - Beta
Classifier: Environment :: Web Environment
Classifier: Framework :: Zope3
Classifier: Intended Audience :: Other Audience
Classifier: License :: OSI Approved :: GNU General Public License (GPL)
Classifier: Operating System :: OS Independent
Classifier: Programming Language :: Python
